examples/check_servers.py
examples/numbers.py
pyteamtalk-0.2.dist-info/licenses/license.md
teamtalk/__init__.py
teamtalk/teamtalk.py
pyteamtalk-0.2.dist-info/METADATA
pyteamtalk-0.2.dist-info/WHEEL
pyteamtalk-0.2.dist-info/top_level.txt
pyteamtalk-0.2.dist-info/RECORD
