Metadata-Version: 2.4
Name: PyTeamTalk
Version: 0.2
Summary: A human-friendly wrapper around the TeamTalk 5 TCP API
Author-email: Carter Temm <crtbraille@gmail.com>
License-Expression: MIT
Project-URL: Homepage, http://github.com/cartertemm/pyteamtalk
Classifier: Programming Language :: Python :: 3
Classifier: Operating System :: OS Independent
Classifier: Development Status :: 4 - Beta
Requires-Python: >=3
License-File: license.md
Requires-Dist: telnetlib-313-and-up; python_version >= "3.13"
Dynamic: license-file
